{"status":"ok","message":"成功","groups":[{"groupDesc":{"attr":"攻击","members":"吕布(群)、吕布(汉)、貂蝉(汉)、高顺(群)、吕姬(群)、张辽(群)、陈宫(群)","name":"温侯无双"},"groupImgId2":["100003","100060"],"groupImgId3":[],"groupName":"温侯无双","groupImgId":["100010","100005","100115","100055","100050","100109"],"groupId":38},{"groupDesc":{"attr":"攻击、谋略","members":"张角(群)、张梁(群)、张宝(群)","name":"苍天已死"},"groupImgId2":[],"groupImgId3":[],"groupName":"苍天已死","groupImgId":["100008","100051","100430"],"groupId":24},{"groupDesc":{"attr":"攻击、射程","members":"董卓(群)、曹操(汉)、王允(汉)","name":"行刺太师"},"groupImgId2":[],"groupImgId3":[],"groupName":"行刺太师","groupImgId":["100009","100042","100105"],"groupId":36},{"groupDesc":{"attr":"速度","members":"马超(群)、贾诩(群)、马超(蜀)、韩遂(群)","name":"叔侄阋墙"},"groupImgId2":["100140"],"groupImgId3":[],"groupName":"叔侄阋墙","groupImgId":["100013","100011","100127"],"groupId":37},{"groupDesc":{"attr":"防御","members":"张飞(蜀)、刘备(蜀)、关羽(蜀)","name":"桃园结义"},"groupImgId2":["100068"],"groupImgId3":[],"groupName":"桃园结义","groupImgId":["100022","100016","100065"],"groupId":16},{"groupDesc":{"attr":"谋略","members":"诸葛亮(蜀)、庞统(蜀)、徐庶(蜀)、法正(群)","name":"蜀之智"},"groupImgId2":[],"groupImgId3":[],"groupName":"蜀之智","groupImgId":["100017","100069","100067","100396"],"groupId":14},{"groupDesc":{"attr":"攻击、防御、谋略、速度、攻城","members":"刘备(蜀)、曹操(魏)、孙权(吴)","name":"三足鼎立"},"groupImgId2":[],"groupImgId3":[],"groupName":"三足鼎立","groupImgId":["100016","100023","100030"],"groupId":33},{"groupDesc":{"attr":"谋略","members":"荀彧(魏)、郭嘉(魏)、荀攸(魏)、程昱(魏)","name":"魏之智"},"groupImgId2":[],"groupImgId3":[],"groupName":"魏之智","groupImgId":["100024","100078","100150","100149"],"groupId":10},{"groupDesc":{"attr":"攻击、谋略","members":"曹丕(魏)、曹彰(魏)、曹昂(魏)、曹植(魏)","name":"孟德之子"},"groupImgId2":[],"groupImgId3":[],"groupName":"孟德之子","groupImgId":["100025","100148","000000","000000"],"groupId":13},{"groupDesc":{"attr":"攻击","members":"孙权(吴)、孙坚(吴)、孙策(吴)","name":"枭雄父子"},"groupImgId2":["100088"],"groupImgId3":[],"groupName":"枭雄父子","groupImgId":["100030","100033","100089"],"groupId":17},{"groupDesc":{"attr":"攻击、防御","members":"周瑜(吴)、甘宁(吴)、黄盖(吴)","name":"苦肉计"},"groupImgId2":["100157","100158"],"groupImgId3":[],"groupName":"苦肉计","groupImgId":["100031","100034","100439"],"groupId":19},{"groupDesc":{"attr":"谋略、速度","members":"周瑜(吴)、吕蒙(吴)、陆逊(吴)、鲁肃(吴)","name":"东吴大都督"},"groupImgId2":["100166"],"groupImgId3":[],"groupName":"东吴大都督","groupImgId":["100031","100035","100092","100163"],"groupId":20},{"groupDesc":{"attr":"谋略","members":"周瑜(吴)、大乔(吴)、小乔(吴)、孙策(吴)","name":"二乔"},"groupImgId2":[],"groupImgId3":[],"groupName":"二乔","groupImgId":["100031","100095","100094","100089"],"groupId":18},{"groupDesc":{"attr":"攻击、谋略","members":"张春华(魏)、王异(魏)、孙尚香(吴)","name":"惧内"},"groupImgId2":[],"groupImgId3":[],"groupName":"惧内","groupImgId":["100029","100028","100036"],"groupId":32},{"groupDesc":{"attr":"防御","members":"灵帝(汉)、何太后(汉)、少帝(汉)","name":"少帝父子"},"groupImgId2":[],"groupImgId3":[],"groupName":"少帝父子","groupImgId":["100101","100037","100414"],"groupId":3},{"groupDesc":{"attr":"防御、速度","members":"卢植(汉)、皇甫嵩(汉)、张奂(汉)、朱儁(汉)","name":"末路尽忠"},"groupImgId2":[],"groupImgId3":[],"groupName":"末路尽忠","groupImgId":["100007","100039","100041","100040"],"groupId":7},{"groupDesc":{"attr":"射程","members":"何太后(汉)、十常侍(汉)、何进(汉)","name":"宦官斗外戚"},"groupImgId2":[],"groupImgId3":[],"groupName":"宦官斗外戚","groupImgId":["100037","100002","100098"],"groupId":8},{"groupDesc":{"attr":"谋略、速度","members":"何太后(汉)、郭皇后(魏)、穆皇后(蜀)、甘皇后(蜀)、吴夫人(吴)、丁夫人(魏)","name":"母仪天下"},"groupImgId2":[],"groupImgId3":[],"groupName":"母仪天下","groupImgId":["100037","100075","100070","100063","100091","100077"],"groupId":39},{"groupDesc":{"attr":"防御","members":"灵帝(汉)、献帝(汉)、少帝(汉)","name":"汉朝皇族"},"groupImgId2":[],"groupImgId3":[],"groupName":"汉朝皇族","groupImgId":["100101","100001","100414"],"groupId":1},{"groupDesc":{"attr":"防御","members":"灵帝(汉)、献帝(汉)、王美人(汉)","name":"献帝父子"},"groupImgId2":[],"groupImgId3":[],"groupName":"献帝父子","groupImgId":["100101","100001","100038"],"groupId":2},{"groupDesc":{"attr":"攻击","members":"张飞(蜀)、赵云(蜀)、关羽(蜀)、马超(蜀)、黄忠(蜀)","name":"五虎上将"},"groupImgId2":["100068"],"groupImgId3":[],"groupName":"五虎上将","groupImgId":["100022","100021","100065","100140","100130"],"groupId":15},{"groupDesc":{"attr":"攻击","members":"张辽(魏)、张郃(魏)、徐晃(魏)、于禁(魏)、乐进(魏)","name":"五子良将"},"groupImgId2":[],"groupImgId3":[],"groupName":"五子良将","groupImgId":["100027","100083","100421","100143","100144"],"groupId":12},{"groupDesc":{"attr":"防御、速度","members":"马云禄(蜀)、马超(群)、马腾(群)、马岱(蜀)、马超(蜀)","name":"驰马西凉"},"groupImgId2":["100140"],"groupImgId3":[],"groupName":"驰马西凉","groupImgId":["100019","100013","100062","100139"],"groupId":27},{"groupDesc":{"attr":"防御、速度","members":"甘宁(吴)、周泰(吴)、徐盛(吴)","name":"纵横江海"},"groupImgId2":["100157"],"groupImgId3":[],"groupName":"纵横江海","groupImgId":["100034","100086","100087"],"groupId":23},{"groupDesc":{"attr":"攻击、速度","members":"夏侯渊(魏)、曹仁(魏)、夏侯惇(魏)、曹洪(魏)","name":"魏武强将"},"groupImgId2":["100435"],"groupImgId3":["100420"],"groupName":"魏武强将","groupImgId":["100145","100085","100079","100147"],"groupId":11},{"groupDesc":{"attr":"攻击","members":"皇甫嵩(汉)、朱儁(汉)、何进(汉)","name":"汉朝官军"},"groupImgId2":[],"groupImgId3":[],"groupName":"汉朝官军","groupImgId":["100039","100040","100098"],"groupId":6},{"groupDesc":{"attr":"攻城、射程","members":"管亥(群)、张曼成(群)、周仓(群)","name":"黄巾强将"},"groupImgId2":[],"groupImgId3":[],"groupName":"黄巾强将","groupImgId":["100052","100054","100111"],"groupId":26},{"groupDesc":{"attr":"攻击、防御","members":"韩当(吴)、程普(吴)、蒋钦(吴)、黄盖(吴)","name":"东吴老将"},"groupImgId2":["100158"],"groupImgId3":[],"groupName":"东吴老将","groupImgId":["100156","100162","100159","100439"],"groupId":21},{"groupDesc":{"attr":"攻击","members":"刘备(汉)、曹操(汉)、孙坚(汉)","name":"潜龙在渊"},"groupImgId2":[],"groupImgId3":[],"groupName":"潜龙在渊","groupImgId":["100044","100042","100043"],"groupId":9},{"groupDesc":{"attr":"防御、攻城","members":"黄忠(蜀)、严颜(蜀)、黄盖(吴)","name":"老当益壮"},"groupImgId2":["100158"],"groupImgId3":[],"groupName":"老当益壮","groupImgId":["100130","100134","100439"],"groupId":30},{"groupDesc":{"attr":"谋略","members":"鲁肃(吴)、步骘(吴)、陆逊(吴)、张昭(吴)","name":"吴之智"},"groupImgId2":[],"groupImgId3":[],"groupName":"吴之智","groupImgId":["100163","100096","100092","100161"],"groupId":22},{"groupDesc":{"attr":"攻击、防御","members":"颜良(群)、张郃(群)、文丑(群)、高览(群)","name":"河北四庭柱"},"groupImgId2":[],"groupImgId3":[],"groupName":"河北四庭柱","groupImgId":["100058","100123","100059","100119"],"groupId":29},{"groupDesc":{"attr":"谋略","members":"程昱(魏)、鲁肃(吴)、法正(群)","name":"三国智将"},"groupImgId2":[],"groupImgId3":[],"groupName":"三国智将","groupImgId":["100149","100163","100396"],"groupId":35},{"groupDesc":{"attr":"防御、速度","members":"王烈(汉)、刘虞(汉)、王允(汉)","name":"汉朝仕官"},"groupImgId2":[],"groupImgId3":[],"groupName":"汉朝仕官","groupImgId":["100102","100104","100105"],"groupId":5},{"groupDesc":{"attr":"防御","members":"刘焉(汉)、刘表(汉)、刘虞(汉)","name":"偏安一隅"},"groupImgId2":[],"groupImgId3":[],"groupName":"偏安一隅","groupImgId":["100285","100107","100104"],"groupId":34},{"groupDesc":{"attr":"谋略、射程","members":"审配(群)、许攸(群)、郭图(群)","name":"勾心斗角"},"groupImgId2":[],"groupImgId3":[],"groupName":"勾心斗角","groupImgId":["100186","000000","000000"],"groupId":31},{"groupDesc":{"attr":"攻击、防御、速度、攻城","members":"程远志(群)、邓茂(群)、马元义(群)、裴元绍(群)","name":"黄巾游勇"},"groupImgId2":[],"groupImgId3":[],"groupName":"黄巾游勇","groupImgId":["100181","100270","100183","100182"],"groupId":25},{"groupDesc":{"attr":"速度","members":"张横(群)、成宜(群)、李堪(群)、马玩(群)、杨秋(群)、候选(群)、程银(群)、颜良(群)","name":"旗本八骑"},"groupImgId2":[],"groupImgId3":[],"groupName":"旗本八骑","groupImgId":["100342","100348","100343","100344","100345","100346","100347"],"groupId":28}]}